Metadata-Version: 2.1
Name: Proxy-List-Scrapper
Version: 0.1.3
Summary: proxy list scrapper from various websites. they gives the free proxies for temporary use.
Home-page: UNKNOWN
Author: Sameer Narkhede
Author-email: narkhedesam@gmail.com
License: MIT License
Platform: UNKNOWN
